{
  "0": [
    1,
    2,
    48,
    141,
    159,
    196,
    202,
    208,
    213
  ],
  "1": [
    2,
    3,
    99,
    204
  ],
  "2": [
    7,
    15,
    37,
    72,
    167
  ],
  "3": [
    4,
    5,
    38,
    161,
    197,
    244
  ],
  "4": [
    5,
    49,
    121,
    228,
    239,
    270
  ],
  "5": [
    66,
    84,
    127,
    257
  ],
  "6": [
    7,
    8,
    43,
    168
  ],
  "7": [
    8,
    81,
    93,
    152,
    221
  ],
  "8": [
    20,
    46,
    59,
    98,
    124,
    171,
    191,
    267
  ],
  "9": [
    10,
    11,
    56,
    60,
    67,
    186,
    209,
    219
  ],
  "10": [
    11,
    70,
    87,
    140,
    144,
    172,
    185,
    194,
    222
  ],
  "11": [
    18,
    34,
    74,
    107,
    111,
    187
  ],
  "12": [
    13,
    14,
    35,
    105,
    151,
    169,
    236,
    269
  ],
  "13": [
    14,
    39,
    57,
    89,
    122,
    129,
    132,
    154,
    156,
    184,
    214
  ],
  "14": [
    24,
    47,
    53,
    110,
    114,
    126,
    147,
    201
  ],
  "15": [
    16,
    17,
    81,
    93,
    152,
    221
  ],
  "16": [
    17,
    48,
    141,
    159,
    196,
    202,
    208,
    213
  ],
  "17": [
    70,
    87,
    140,
    144,
    172,
    185,
    194,
    222
  ],
  "18": [
    19,
    20,
    29,
    62,
    90,
    183,
    212,
    218,
    247
  ],
  "19": [
    20,
    70,
    87,
    140,
    144,
    172,
    185,
    194,
    222
  ],
  "20": [
    33,
    134,
    198,
    243
  ],
  "21": [
    22,
    23,
    28,
    83,
    92,
    104,
    116,
    119,
    190,
    215
  ],
  "22": [
    23,
    25,
    58,
    73,
    120,
    136,
    165,
    230,
    253,
    256,
    261,
    265
  ],
  "23": [
    35,
    105,
    151,
    169,
    236,
    269
  ],
  "24": [
    25,
    26,
    44,
    179,
    217,
    229,
    235,
    238,
    241,
    272
  ],
  "25": [
    26,
    50,
    88,
    91,
    94,
    115,
    203,
    216,
    232
  ],
  "26": [
    30,
    41,
    95,
    130,
    180,
    224,
    252
  ],
  "27": [
    28,
    29,
    43,
    168
  ],
  "28": [
    29,
    78,
    108,
    137,
    138,
    174,
    231,
    237,
    242,
    258,
    262,
    268
  ],
  "29": [
    34,
    74,
    107,
    111,
    187
  ],
  "30": [
    31,
    32,
    77,
    128,
    250,
    260
  ],
  "31": [
    32,
    35,
    105,
    151,
    169,
    236,
    269
  ],
  "32": [
    43,
    168
  ],
  "33": [
    34,
    35,
    46,
    59,
    98,
    124,
    171,
    191,
    267
  ],
  "34": [
    35,
    62,
    90,
    183,
    212,
    218,
    247
  ],
  "35": [
    133,
    146,
    148
  ],
  "36": [
    37,
    38,
    49,
    121,
    228,
    239,
    270
  ],
  "37": [
    38,
    81,
    93,
    152,
    221
  ],
  "38": [
    99,
    204
  ],
  "39": [
    40,
    41,
    160,
    199,
    206
  ],
  "40": [
    41,
    56,
    60,
    67,
    186,
    209,
    219
  ],
  "41": [
    77,
    128,
    250,
    260
  ],
  "42": [
    43,
    44,
    52,
    55,
    97,
    102,
    109,
    135,
    143,
    158,
    162,
    227,
    233,
    246,
    259
  ],
  "43": [
    44,
    82,
    85,
    112,
    157,
    163,
    173,
    176,
    192,
    271
  ],
  "44": [
    47,
    53,
    110,
    114,
    126,
    147,
    201
  ],
  "45": [
    46,
    47,
    54,
    79,
    182,
    188,
    207,
    245
  ],
  "46": [
    47,
    134,
    198,
    243
  ],
  "47": [
    179,
    217,
    229,
    235,
    238,
    241,
    272
  ],
  "48": [
    49,
    50,
    61,
    80,
    113,
    131,
    181,
    240
  ],
  "49": [
    50,
    51,
    205,
    220
  ],
  "50": [
    58,
    73,
    120,
    136,
    165,
    230,
    253,
    256,
    261,
    265
  ],
  "51": [
    52,
    53,
    121,
    228,
    239,
    270
  ],
  "52": [
    53,
    65,
    76,
    145,
    149,
    251,
    263
  ],
  "53": [
    179,
    217,
    229,
    235,
    238,
    241,
    272
  ],
  "54": [
    55,
    56,
    69,
    142,
    164,
    175,
    200,
    211,
    266
  ],
  "55": [
    56,
    65,
    76,
    145,
    149,
    251,
    263
  ],
  "56": [
    71,
    125,
    150,
    177,
    210,
    264
  ],
  "57": [
    58,
    59,
    160,
    199,
    206
  ],
  "58": [
    59,
    88,
    91,
    94,
    115,
    203,
    216,
    232
  ],
  "59": [
    134,
    198,
    243
  ],
  "60": [
    61,
    62,
    71,
    125,
    150,
    177,
    210,
    264
  ],
  "61": [
    62,
    141,
    159,
    196,
    202,
    208,
    213
  ],
  "62": [
    74,
    107,
    111,
    187
  ],
  "63": [
    64,
    65,
    66,
    84,
    127,
    257
  ],
  "64": [
    65,
    86,
    96
  ],
  "65": [
    97,
    102,
    109,
    135,
    143,
    158,
    162,
    227,
    233,
    246,
    259
  ],
  "66": [
    67,
    68,
    75,
    103,
    106,
    117,
    139,
    193,
    223,
    254
  ],
  "67": [
    68,
    71,
    125,
    150,
    177,
    210,
    264
  ],
  "68": [
    101,
    118,
    153,
    225,
    234,
    249
  ],
  "69": [
    70,
    71,
    79,
    182,
    188,
    207,
    245
  ],
  "70": [
    71,
    155,
    178,
    189,
    195,
    255
  ],
  "71": [
    186,
    209,
    219
  ],
  "72": [
    73,
    74,
    81,
    93,
    152,
    221
  ],
  "73": [
    74,
    88,
    91,
    94,
    115,
    203,
    216,
    232
  ],
  "74": [
    90,
    183,
    212,
    218,
    247
  ],
  "75": [
    76,
    77,
    84,
    127,
    257
  ],
  "76": [
    77,
    97,
    102,
    109,
    135,
    143,
    158,
    162,
    227,
    233,
    246,
    259
  ],
  "77": [
    95,
    130,
    180,
    224,
    252
  ],
  "78": [
    79,
    80,
    83,
    92,
    104,
    116,
    119,
    190,
    215
  ],
  "79": [
    80,
    142,
    164,
    175,
    200,
    211,
    266
  ],
  "80": [
    141,
    159,
    196,
    202,
    208,
    213
  ],
  "81": [
    82,
    83,
    167
  ],
  "82": [
    83,
    168
  ],
  "83": [
    108,
    137,
    138,
    174,
    231,
    237,
    242,
    258,
    262,
    268
  ],
  "84": [
    85,
    86,
    103,
    106,
    117,
    139,
    193,
    223,
    254
  ],
  "85": [
    86,
    168
  ],
  "86": [
    100,
    166,
    226
  ],
  "87": [
    88,
    89,
    155,
    178,
    189,
    195,
    255
  ],
  "88": [
    89,
    120,
    136,
    165,
    230,
    253,
    256,
    261,
    265
  ],
  "89": [
    160,
    199,
    206
  ],
  "90": [
    91,
    92,
    107,
    111,
    187
  ],
  "91": [
    92,
    120,
    136,
    165,
    230,
    253,
    256,
    261,
    265
  ],
  "92": [
    108,
    137,
    138,
    174,
    231,
    237,
    242,
    258,
    262,
    268
  ],
  "93": [
    94,
    95,
    167
  ],
  "94": [
    95,
    120,
    136,
    165,
    230,
    253,
    256,
    261,
    265
  ],
  "95": [
    128,
    250,
    260
  ],
  "96": [
    97,
    98,
    100,
    166,
    226
  ],
  "97": [
    98,
    145,
    149,
    251,
    263
  ],
  "98": [
    134,
    198,
    243
  ],
  "99": [
    100,
    101,
    161,
    197,
    244
  ],
  "100": [
    101
  ],
  "101": [
    123,
    170,
    248
  ],
  "102": [
    103,
    104,
    145,
    149,
    251,
    263
  ],
  "103": [
    104,
    127,
    257
  ],
  "104": [
    108,
    137,
    138,
    174,
    231,
    237,
    242,
    258,
    262,
    268
  ],
  "105": [
    106,
    107,
    133,
    146,
    148
  ],
  "106": [
    107,
    127,
    257
  ],
  "107": [
    183,
    212,
    218,
    247
  ],
  "108": [
    109,
    110,
    116,
    119,
    190,
    215
  ],
  "109": [
    110,
    145,
    149,
    251,
    263
  ],
  "110": [
    179,
    217,
    229,
    235,
    238,
    241,
    272
  ],
  "111": [
    112,
    113,
    183,
    212,
    218,
    247
  ],
  "112": [
    113,
    168
  ],
  "113": [
    141,
    159,
    196,
    202,
    208,
    213
  ],
  "114": [
    115,
    116,
    179,
    217,
    229,
    235,
    238,
    241,
    272
  ],
  "115": [
    116,
    120,
    136,
    165,
    230,
    253,
    256,
    261,
    265
  ],
  "116": [
    137,
    138,
    174,
    231,
    237,
    242,
    258,
    262,
    268
  ],
  "117": [
    118,
    119,
    127,
    257
  ],
  "118": [
    119,
    123,
    170,
    248
  ],
  "119": [
    137,
    138,
    174,
    231,
    237,
    242,
    258,
    262,
    268
  ],
  "120": [
    121,
    122,
    203,
    216,
    232
  ],
  "121": [
    122,
    205,
    220
  ],
  "122": [
    160,
    199,
    206
  ],
  "123": [
    124,
    125,
    153,
    225,
    234,
    249
  ],
  "124": [
    125,
    134,
    198,
    243
  ],
  "125": [
    186,
    209,
    219
  ],
  "126": [
    127,
    128,
    179,
    217,
    229,
    235,
    238,
    241,
    272
  ],
  "127": [
    128,
    139,
    193,
    223,
    254
  ],
  "128": [
    130,
    180,
    224,
    252
  ],
  "129": [
    130,
    131,
    160,
    199,
    206
  ],
  "130": [
    131,
    250,
    260
  ],
  "131": [
    141,
    159,
    196,
    202,
    208,
    213
  ],
  "132": [
    133,
    134,
    160,
    199,
    206
  ],
  "133": [
    134,
    151,
    169,
    236,
    269
  ],
  "134": [
    171,
    191,
    267
  ],
  "135": [
    136,
    137,
    145,
    149,
    251,
    263
  ],
  "136": [
    137,
    203,
    216,
    232
  ],
  "137": [
    190,
    215
  ],
  "138": [
    139,
    140,
    190,
    215
  ],
  "139": [
    140,
    257
  ],
  "140": [
    155,
    178,
    189,
    195,
    255
  ],
  "141": [
    142,
    143,
    181,
    240
  ],
  "142": [
    143,
    182,
    188,
    207,
    245
  ],
  "143": [
    145,
    149,
    251,
    263
  ],
  "144": [
    145,
    146,
    155,
    178,
    189,
    195,
    255
  ],
  "145": [
    146,
    158,
    162,
    227,
    233,
    246,
    259
  ],
  "146": [
    151,
    169,
    236,
    269
  ],
  "147": [
    148,
    149,
    179,
    217,
    229,
    235,
    238,
    241,
    272
  ],
  "148": [
    149,
    151,
    169,
    236,
    269
  ],
  "149": [
    158,
    162,
    227,
    233,
    246,
    259
  ],
  "150": [
    151,
    152,
    186,
    209,
    219
  ],
  "151": [
    152
  ],
  "152": [
    167
  ],
  "153": [
    154,
    155,
    170,
    248
  ],
  "154": [
    155,
    160,
    199,
    206
  ],
  "155": [
    172,
    185,
    194,
    222
  ],
  "156": [
    157,
    158,
    160,
    199,
    206
  ],
  "157": [
    158,
    168
  ],
  "158": [
    251,
    263
  ],
  "159": [
    160,
    161,
    181,
    240
  ],
  "160": [
    161,
    184,
    214
  ],
  "161": [
    204
  ],
  "162": [
    163,
    164,
    251,
    263
  ],
  "163": [
    164,
    168
  ],
  "164": [
    182,
    188,
    207,
    245
  ],
  "165": [
    166,
    167,
    203,
    216,
    232
  ],
  "166": [
    167
  ],
  "167": [
    221
  ],
  "168": [
    169,
    170,
    173,
    176,
    192,
    271
  ],
  "169": [
    170
  ],
  "170": [
    225,
    234,
    249
  ],
  "171": [
    172,
    173,
    198,
    243
  ],
  "172": [
    173,
    178,
    189,
    195,
    255
  ],
  "173": [],
  "174": [
    175,
    176,
    190,
    215
  ],
  "175": [
    176,
    182,
    188,
    207,
    245
  ],
  "176": [],
  "177": [
    178,
    179,
    186,
    209,
    219
  ],
  "178": [
    179,
    185,
    194,
    222
  ],
  "179": [
    201
  ],
  "180": [
    181,
    182,
    250,
    260
  ],
  "181": [
    182,
    196,
    202,
    208,
    213
  ],
  "182": [
    200,
    211,
    266
  ],
  "183": [
    184,
    185,
    187
  ],
  "184": [
    185,
    199,
    206
  ],
  "185": [
    189,
    195,
    255
  ],
  "186": [
    187,
    188,
    210,
    264
  ],
  "187": [
    188,
    212,
    218,
    247
  ],
  "188": [
    200,
    211,
    266
  ],
  "189": [
    190,
    191,
    194,
    222
  ],
  "190": [
    191,
    231,
    237,
    242,
    258,
    262,
    268
  ],
  "191": [
    198,
    243
  ],
  "192": [
    193,
    194
  ],
  "193": [
    194,
    257
  ],
  "194": [
    195,
    255
  ],
  "195": [
    196,
    197,
    222
  ],
  "196": [
    197,
    240
  ],
  "197": [
    204
  ],
  "198": [
    199,
    200,
    267
  ],
  "199": [
    200,
    214
  ],
  "200": [
    207,
    245
  ],
  "201": [
    202,
    203,
    217,
    229,
    235,
    238,
    241,
    272
  ],
  "202": [
    203,
    240
  ],
  "203": [
    230,
    253,
    256,
    261,
    265
  ],
  "204": [
    205,
    206,
    244
  ],
  "205": [
    206,
    228,
    239,
    270
  ],
  "206": [
    214
  ],
  "207": [
    208,
    209,
    211,
    266
  ],
  "208": [
    209,
    240
  ],
  "209": [
    210,
    264
  ],
  "210": [
    211,
    212,
    219
  ],
  "211": [
    212,
    245
  ],
  "212": [],
  "213": [
    214,
    215,
    240
  ],
  "214": [
    215
  ],
  "215": [
    231,
    237,
    242,
    258,
    262,
    268
  ],
  "216": [
    217,
    218,
    230,
    253,
    256,
    261,
    265
  ],
  "217": [
    218
  ],
  "218": [],
  "219": [
    220,
    221,
    264
  ],
  "220": [
    221,
    228,
    239,
    270
  ],
  "221": [],
  "222": [
    223,
    224,
    255
  ],
  "223": [
    224,
    257
  ],
  "224": [
    250,
    260
  ],
  "225": [
    226,
    227,
    248
  ],
  "226": [
    227
  ],
  "227": [
    251,
    263
  ],
  "228": [
    229,
    230
  ],
  "229": [
    230
  ],
  "230": [
    232
  ],
  "231": [
    232,
    233
  ],
  "232": [
    233,
    253,
    256,
    261,
    265
  ],
  "233": [
    251,
    263
  ],
  "234": [
    235,
    236,
    248
  ],
  "235": [
    236
  ],
  "236": [],
  "237": [
    238,
    239
  ],
  "238": [
    239
  ],
  "239": [],
  "240": [
    241,
    242
  ],
  "241": [
    242
  ],
  "242": [],
  "243": [
    244,
    245,
    267
  ],
  "244": [
    245
  ],
  "245": [
    266
  ],
  "246": [
    247,
    248,
    251,
    263
  ],
  "247": [
    248
  ],
  "248": [
    249
  ],
  "249": [
    250,
    251
  ],
  "250": [
    251,
    252
  ],
  "251": [
    259
  ],
  "252": [
    253,
    254,
    260
  ],
  "253": [
    254
  ],
  "254": [
    257
  ],
  "255": [
    256,
    257
  ],
  "256": [
    257
  ],
  "257": [],
  "258": [
    259,
    260
  ],
  "259": [
    260,
    263
  ],
  "260": [],
  "261": [
    262,
    263
  ],
  "262": [
    263
  ],
  "263": [],
  "264": [
    265,
    266
  ],
  "265": [
    266
  ],
  "266": [],
  "267": [
    268,
    269
  ],
  "268": [
    269
  ],
  "269": [],
  "270": [
    271,
    272
  ],
  "271": [
    272
  ],
  "272": []
}