{
  "0": [
    1,
    2,
    26,
    54,
    151,
    165
  ],
  "1": [
    2,
    188,
    207,
    214,
    254,
    272
  ],
  "2": [
    41,
    44,
    89,
    119,
    199,
    233,
    260,
    265
  ],
  "3": [
    4,
    5,
    41,
    44,
    89,
    119,
    199,
    233,
    260,
    265
  ],
  "4": [
    5,
    62,
    69,
    113,
    126,
    139,
    179,
    202
  ],
  "5": [
    81,
    125,
    128,
    159,
    167,
    177,
    226
  ],
  "6": [
    7,
    8,
    14,
    75,
    185,
    187,
    237
  ],
  "7": [
    8,
    48,
    57,
    78,
    92,
    98,
    111,
    131,
    155,
    184,
    189,
    200,
    235,
    252,
    267,
    271
  ],
  "8": [
    62,
    69,
    113,
    126,
    139,
    179,
    202
  ],
  "9": [
    10,
    11,
    14,
    75,
    185,
    187,
    237
  ],
  "10": [
    11,
    23,
    172,
    241
  ],
  "11": [
    60,
    110,
    135,
    143,
    153,
    197,
    253,
    255
  ],
  "12": [
    13,
    14,
    25,
    34,
    36,
    59,
    67,
    115,
    136,
    142,
    170,
    256
  ],
  "13": [
    14,
    20,
    96,
    114,
    238
  ],
  "14": [
    79,
    118,
    209,
    213,
    240
  ],
  "15": [
    16,
    17,
    38,
    46,
    64,
    103,
    168,
    223
  ],
  "16": [
    17,
    77,
    99,
    154,
    181,
    212,
    266
  ],
  "17": [
    76,
    93,
    193,
    210,
    243,
    258,
    270
  ],
  "18": [
    19,
    20,
    35,
    45,
    56,
    66,
    71,
    91,
    107,
    186,
    216,
    239,
    248,
    264
  ],
  "19": [
    20,
    25,
    34,
    36,
    59,
    67,
    115,
    136,
    142,
    170,
    256
  ],
  "20": [
    88,
    132,
    145,
    178,
    217
  ],
  "21": [
    22,
    23,
    76,
    93,
    193,
    210,
    243,
    258,
    270
  ],
  "22": [
    23,
    29,
    40,
    47,
    70,
    84,
    169,
    229,
    262
  ],
  "23": [
    109,
    198,
    221,
    222,
    246
  ],
  "24": [
    25,
    26,
    76,
    93,
    193,
    210,
    243,
    258,
    270
  ],
  "25": [
    26,
    51,
    73,
    94,
    97,
    104,
    149,
    160,
    204,
    220
  ],
  "26": [
    31,
    120,
    156,
    227
  ],
  "27": [
    28,
    29,
    48,
    57,
    78,
    92,
    98,
    111,
    131,
    155,
    184,
    189,
    200,
    235,
    252,
    267,
    271
  ],
  "28": [
    29,
    35,
    45,
    56,
    66,
    71,
    91,
    107,
    186,
    216,
    239,
    248,
    264
  ],
  "29": [
    49,
    144,
    183,
    191
  ],
  "30": [
    31,
    32,
    38,
    46,
    64,
    103,
    168,
    223
  ],
  "31": [
    32,
    54,
    151,
    165
  ],
  "32": [
    85,
    105,
    117,
    141,
    162,
    173,
    211,
    219,
    232,
    249
  ],
  "33": [
    34,
    35,
    48,
    57,
    78,
    92,
    98,
    111,
    131,
    155,
    184,
    189,
    200,
    235,
    252,
    267,
    271
  ],
  "34": [
    35,
    51,
    73,
    94,
    97,
    104,
    149,
    160,
    204,
    220
  ],
  "35": [
    61,
    82,
    100,
    127,
    148,
    150,
    268
  ],
  "36": [
    37,
    38,
    51,
    73,
    94,
    97,
    104,
    149,
    160,
    204,
    220
  ],
  "37": [
    38,
    76,
    93,
    193,
    210,
    243,
    258,
    270
  ],
  "38": [
    87,
    176,
    201,
    236
  ],
  "39": [
    40,
    41,
    60,
    110,
    135,
    143,
    153,
    197,
    253,
    255
  ],
  "40": [
    41,
    49,
    144,
    183,
    191
  ],
  "41": [
    161,
    166,
    208,
    225,
    244
  ],
  "42": [
    43,
    44,
    129,
    175,
    230
  ],
  "43": [
    44,
    48,
    57,
    78,
    92,
    98,
    111,
    131,
    155,
    184,
    189,
    200,
    235,
    252,
    267,
    271
  ],
  "44": [
    161,
    166,
    208,
    225,
    244
  ],
  "45": [
    46,
    47,
    61,
    82,
    100,
    127,
    148,
    150,
    268
  ],
  "46": [
    47,
    87,
    176,
    201,
    236
  ],
  "47": [
    49,
    144,
    183,
    191
  ],
  "48": [
    49,
    50,
    72,
    121,
    140,
    174,
    180,
    205
  ],
  "49": [
    50,
    70,
    84,
    169,
    229,
    262
  ],
  "50": [
    60,
    110,
    135,
    143,
    153,
    197,
    253,
    255
  ],
  "51": [
    52,
    53,
    59,
    67,
    115,
    136,
    142,
    170,
    256
  ],
  "52": [
    53,
    106,
    152,
    257
  ],
  "53": [
    85,
    105,
    117,
    141,
    162,
    173,
    211,
    219,
    232,
    249
  ],
  "54": [
    55,
    56,
    120,
    156,
    227
  ],
  "55": [
    56,
    76,
    93,
    193,
    210,
    243,
    258,
    270
  ],
  "56": [
    61,
    82,
    100,
    127,
    148,
    150,
    268
  ],
  "57": [
    58,
    59,
    72,
    121,
    140,
    174,
    180,
    205
  ],
  "58": [
    59,
    188,
    207,
    214,
    254,
    272
  ],
  "59": [
    73,
    94,
    97,
    104,
    149,
    160,
    204,
    220
  ],
  "60": [
    61,
    62,
    74,
    80,
    157,
    182,
    203,
    228,
    245,
    247
  ],
  "61": [
    62,
    66,
    71,
    91,
    107,
    186,
    216,
    239,
    248,
    264
  ],
  "62": [
    63,
    108,
    134,
    171,
    194,
    251
  ],
  "63": [
    64,
    65,
    69,
    113,
    126,
    139,
    179,
    202
  ],
  "64": [
    65,
    87,
    176,
    201,
    236
  ],
  "65": [
    95,
    101,
    146,
    242,
    250
  ],
  "66": [
    67,
    68,
    82,
    100,
    127,
    148,
    150,
    268
  ],
  "67": [
    68,
    73,
    94,
    97,
    104,
    149,
    160,
    204,
    220
  ],
  "68": [
    95,
    101,
    146,
    242,
    250
  ],
  "69": [
    70,
    71,
    108,
    134,
    171,
    194,
    251
  ],
  "70": [
    71,
    144,
    183,
    191
  ],
  "71": [
    82,
    100,
    127,
    148,
    150,
    268
  ],
  "72": [
    73,
    74,
    78,
    92,
    98,
    111,
    131,
    155,
    184,
    189,
    200,
    235,
    252,
    267,
    271
  ],
  "73": [
    74,
    115,
    136,
    142,
    170,
    256
  ],
  "74": [
    110,
    135,
    143,
    153,
    197,
    253,
    255
  ],
  "75": [
    76,
    77,
    79,
    118,
    209,
    213,
    240
  ],
  "76": [
    77,
    116,
    124,
    195,
    206,
    215,
    218
  ],
  "77": [
    224,
    261
  ],
  "78": [
    79,
    80,
    121,
    140,
    174,
    180,
    205
  ],
  "79": [
    80,
    185,
    187,
    237
  ],
  "80": [
    110,
    135,
    143,
    153,
    197,
    253,
    255
  ],
  "81": [
    82,
    83,
    86,
    133,
    138,
    158,
    196,
    263
  ],
  "82": [
    83,
    91,
    107,
    186,
    216,
    239,
    248,
    264
  ],
  "83": [
    188,
    207,
    214,
    254,
    272
  ],
  "84": [
    85,
    86,
    144,
    183,
    191
  ],
  "85": [
    86,
    112,
    122
  ],
  "86": [
    125,
    128,
    159,
    167,
    177,
    226
  ],
  "87": [
    88,
    89,
    103,
    168,
    223
  ],
  "88": [
    89,
    96,
    114,
    238
  ],
  "89": [
    161,
    166,
    208,
    225,
    244
  ],
  "90": [
    91,
    92,
    95,
    101,
    146,
    242,
    250
  ],
  "91": [
    92,
    100,
    127,
    148,
    150,
    268
  ],
  "92": [
    121,
    140,
    174,
    180,
    205
  ],
  "93": [
    94,
    95,
    116,
    124,
    195,
    206,
    215,
    218
  ],
  "94": [
    95,
    115,
    136,
    142,
    170,
    256
  ],
  "95": [
    137,
    192,
    234
  ],
  "96": [
    97,
    98,
    132,
    145,
    178,
    217
  ],
  "97": [
    98,
    115,
    136,
    142,
    170,
    256
  ],
  "98": [
    121,
    140,
    174,
    180,
    205
  ],
  "99": [
    100,
    101,
    224,
    261
  ],
  "100": [
    101,
    107,
    186,
    216,
    239,
    248,
    264
  ],
  "101": [
    137,
    192,
    234
  ],
  "102": [
    103,
    104,
    106,
    152,
    257
  ],
  "103": [
    104,
    176,
    201,
    236
  ],
  "104": [
    115,
    136,
    142,
    170,
    256
  ],
  "105": [
    106,
    107,
    112,
    122
  ],
  "106": [
    107,
    123,
    164
  ],
  "107": [
    127,
    148,
    150,
    268
  ],
  "108": [
    109,
    110,
    113,
    126,
    139,
    179,
    202
  ],
  "109": [
    110,
    172,
    241
  ],
  "110": [
    157,
    182,
    203,
    228,
    245,
    247
  ],
  "111": [
    112,
    113,
    121,
    140,
    174,
    180,
    205
  ],
  "112": [
    113,
    117,
    141,
    162,
    173,
    211,
    219,
    232,
    249
  ],
  "113": [
    134,
    171,
    194,
    251
  ],
  "114": [
    115,
    116,
    132,
    145,
    178,
    217
  ],
  "115": [
    116,
    149,
    160,
    204,
    220
  ],
  "116": [
    193,
    210,
    243,
    258,
    270
  ],
  "117": [
    118,
    119,
    122
  ],
  "118": [
    119,
    185,
    187,
    237
  ],
  "119": [
    161,
    166,
    208,
    225,
    244
  ],
  "120": [
    121,
    122,
    151,
    165
  ],
  "121": [
    122,
    131,
    155,
    184,
    189,
    200,
    235,
    252,
    267,
    271
  ],
  "122": [
    141,
    162,
    173,
    211,
    219,
    232,
    249
  ],
  "123": [
    124,
    125,
    152,
    257
  ],
  "124": [
    125,
    193,
    210,
    243,
    258,
    270
  ],
  "125": [
    133,
    138,
    158,
    196,
    263
  ],
  "126": [
    127,
    128,
    134,
    171,
    194,
    251
  ],
  "127": [
    128,
    186,
    216,
    239,
    248,
    264
  ],
  "128": [
    133,
    138,
    158,
    196,
    263
  ],
  "129": [
    130,
    131,
    163,
    231
  ],
  "130": [
    131,
    188,
    207,
    214,
    254,
    272
  ],
  "131": [
    140,
    174,
    180,
    205
  ],
  "132": [
    133,
    134,
    238
  ],
  "133": [
    134,
    159,
    167,
    177,
    226
  ],
  "134": [
    139,
    179,
    202
  ],
  "135": [
    136,
    137,
    157,
    182,
    203,
    228,
    245,
    247
  ],
  "136": [
    137,
    149,
    160,
    204,
    220
  ],
  "137": [
    146,
    242,
    250
  ],
  "138": [
    139,
    140,
    159,
    167,
    177,
    226
  ],
  "139": [
    140,
    171,
    194,
    251
  ],
  "140": [
    155,
    184,
    189,
    200,
    235,
    252,
    267,
    271
  ],
  "141": [
    142,
    143
  ],
  "142": [
    143,
    149,
    160,
    204,
    220
  ],
  "143": [
    157,
    182,
    203,
    228,
    245,
    247
  ],
  "144": [
    145,
    146,
    169,
    229,
    262
  ],
  "145": [
    146,
    238
  ],
  "146": [
    192,
    234
  ],
  "147": [
    148,
    149,
    188,
    207,
    214,
    254,
    272
  ],
  "148": [
    149,
    186,
    216,
    239,
    248,
    264
  ],
  "149": [
    170,
    256
  ],
  "150": [
    151,
    152,
    186,
    216,
    239,
    248,
    264
  ],
  "151": [
    152,
    156,
    227
  ],
  "152": [
    164
  ],
  "153": [
    154,
    155,
    157,
    182,
    203,
    228,
    245,
    247
  ],
  "154": [
    155,
    224,
    261
  ],
  "155": [
    174,
    180,
    205
  ],
  "156": [
    157,
    158,
    165
  ],
  "157": [
    158,
    197,
    253,
    255
  ],
  "158": [
    159,
    167,
    177,
    226
  ],
  "159": [
    160,
    161,
    196,
    263
  ],
  "160": [
    161,
    170,
    256
  ],
  "161": [
    199,
    233,
    260,
    265
  ],
  "162": [
    163,
    164
  ],
  "163": [
    164,
    175,
    230
  ],
  "164": [
    257
  ],
  "165": [
    166,
    167,
    227
  ],
  "166": [
    167,
    199,
    233,
    260,
    265
  ],
  "167": [
    196,
    263
  ],
  "168": [
    169,
    170,
    176,
    201,
    236
  ],
  "169": [
    170,
    183,
    191
  ],
  "170": [
    204,
    220
  ],
  "171": [
    172,
    173,
    179,
    202
  ],
  "172": [
    173,
    198,
    221,
    222,
    246
  ],
  "173": [],
  "174": [
    175,
    176,
    184,
    189,
    200,
    235,
    252,
    267,
    271
  ],
  "175": [
    176,
    231
  ],
  "176": [
    223
  ],
  "177": [
    178,
    179,
    196,
    263
  ],
  "178": [
    179,
    238
  ],
  "179": [
    194,
    251
  ],
  "180": [
    181,
    182,
    184,
    189,
    200,
    235,
    252,
    267,
    271
  ],
  "181": [
    182,
    224,
    261
  ],
  "182": [
    197,
    253,
    255
  ],
  "183": [
    184,
    185,
    229,
    262
  ],
  "184": [
    185,
    205
  ],
  "185": [
    209,
    213,
    240
  ],
  "186": [
    187,
    188,
    268
  ],
  "187": [
    188,
    209,
    213,
    240
  ],
  "188": [
    190,
    259,
    269
  ],
  "189": [
    190,
    191,
    205
  ],
  "190": [
    191,
    207,
    214,
    254,
    272
  ],
  "191": [
    229,
    262
  ],
  "192": [
    193,
    194,
    242,
    250
  ],
  "193": [
    194,
    195,
    206,
    215,
    218
  ],
  "194": [
    202
  ],
  "195": [
    196,
    197,
    210,
    243,
    258,
    270
  ],
  "196": [
    197,
    226
  ],
  "197": [
    203,
    228,
    245,
    247
  ],
  "198": [
    199,
    200,
    241
  ],
  "199": [
    200,
    208,
    225,
    244
  ],
  "200": [
    205
  ],
  "201": [
    202,
    203,
    223
  ],
  "202": [
    203,
    251
  ],
  "203": [
    253,
    255
  ],
  "204": [
    205,
    206,
    256
  ],
  "205": [
    206,
    235,
    252,
    267,
    271
  ],
  "206": [
    210,
    243,
    258,
    270
  ],
  "207": [
    208,
    209,
    259,
    269
  ],
  "208": [
    209,
    233,
    260,
    265
  ],
  "209": [
    237
  ],
  "210": [
    211,
    212,
    215,
    218
  ],
  "211": [
    212
  ],
  "212": [
    224,
    261
  ],
  "213": [
    214,
    215,
    237
  ],
  "214": [
    215,
    259,
    269
  ],
  "215": [
    243,
    258,
    270
  ],
  "216": [
    217,
    218,
    268
  ],
  "217": [
    218,
    238
  ],
  "218": [
    243,
    258,
    270
  ],
  "219": [
    220,
    221
  ],
  "220": [
    221,
    256
  ],
  "221": [
    241
  ],
  "222": [
    223,
    224,
    241
  ],
  "223": [
    224,
    236
  ],
  "224": [
    266
  ],
  "225": [
    226,
    227,
    233,
    260,
    265
  ],
  "226": [
    227,
    263
  ],
  "227": [],
  "228": [
    229,
    230,
    253,
    255
  ],
  "229": [
    230
  ],
  "230": [
    231
  ],
  "231": [
    232,
    233
  ],
  "232": [
    233
  ],
  "233": [
    244
  ],
  "234": [
    235,
    236,
    242,
    250
  ],
  "235": [
    236
  ],
  "236": [],
  "237": [
    238,
    239,
    240
  ],
  "238": [
    239
  ],
  "239": [
    268
  ],
  "240": [
    241,
    242
  ],
  "241": [
    242,
    246
  ],
  "242": [],
  "243": [
    244,
    245
  ],
  "244": [
    245,
    260,
    265
  ],
  "245": [
    253,
    255
  ],
  "246": [
    247,
    248
  ],
  "247": [
    248,
    253,
    255
  ],
  "248": [
    268
  ],
  "249": [
    250,
    251
  ],
  "250": [
    251
  ],
  "251": [],
  "252": [
    253,
    254
  ],
  "253": [
    254
  ],
  "254": [
    259,
    269
  ],
  "255": [
    256,
    257
  ],
  "256": [
    257
  ],
  "257": [],
  "258": [
    259,
    260
  ],
  "259": [
    260,
    272
  ],
  "260": [],
  "261": [
    262,
    263,
    266
  ],
  "262": [
    263
  ],
  "263": [],
  "264": [
    265,
    266,
    268
  ],
  "265": [
    266
  ],
  "266": [],
  "267": [
    268,
    269
  ],
  "268": [
    269
  ],
  "269": [
    272
  ],
  "270": [
    271,
    272
  ],
  "271": [
    272
  ],
  "272": []
}